scan_bundler/__init__.py
scan_bundler/bec_emitter.py
scan_bundler/bluesky_emitter.py
scan_bundler/emitter.py
scan_bundler/scan_bundler.py
scan_bundler/cli/__init__.py
scan_bundler/cli/launch.py
bec_scan_bundler-1.24.1.dist-info/METADATA
bec_scan_bundler-1.24.1.dist-info/WHEEL
bec_scan_bundler-1.24.1.dist-info/entry_points.txt
bec_scan_bundler-1.24.1.dist-info/top_level.txt
bec_scan_bundler-1.24.1.dist-info/RECORD
